{"GlobalPropertiesHash":"9gO1LEl5c5nib78PnwM20jyk36mL1virIx6bt0VwlQ0=","FingerprintPatternsHash":"gq3WsqcKBUGTSNle7RKKyXRIwh7M8ccEqOqYvIzoM04=","PropertyOverridesHash":"8ZRc1sGeVrPBx4lD717BgRaQekyh78QKV9SKsdt638U=","InputHashes":["gb/ThXX/TU6NDeV7SyjJFjNAh4TUhaXV4nOba78LvDg=","K9nkCi3NKzolOAW7pWZR2SZXQ3j1oA8VZ84bEop6Lmo=","LgybJ/xOF8ChsKXsHMr\u002B3NO8UrmM6oQ38adzQNN\u002BKEk=","27sUriLV7k1OME\u002Bh7YCiMSmkee0NU1/MHVGLUiX4i7Q="],"CachedAssets":{"K9nkCi3NKzolOAW7pWZR2SZXQ3j1oA8VZ84bEop6Lmo=":{"Identity":"C:\\Users\\ADMIN\\source\\repos\\ImagenesService\\ImagenesService\\wwwroot\\imagenes\\usuarios\\991d1d3c-c52f-4424-b45a-600b339ca48a.png","SourceId":"ImagenesService","SourceType":"Discovered","ContentRoot":"C:\\Users\\ADMIN\\source\\repos\\ImagenesService\\ImagenesService\\wwwroot\\","BasePath":"_content/ImagenesService","RelativePath":"imagenes/usuarios/991d1d3c-c52f-4424-b45a-600b339ca48a#[.{fingerprint}]?.png","AssetKind":"All","AssetMode":"All","AssetRole":"Primary","AssetMergeBehavior":null,"AssetMergeSource":"","RelatedAsset":null,"AssetTraitName":null,"AssetTraitValue":null,"Fingerprint":"zlpr033jv2","Integrity":"mWl5r2cBJUnLmsuAqOn0GB7PD4lF4nMVuOHZq\u002BtHUMo=","CopyToOutputDirectory":"Never","CopyToPublishDirectory":"PreserveNewest","OriginalItemSpec":"wwwroot\\imagenes\\usuarios\\991d1d3c-c52f-4424-b45a-600b339ca48a.png","FileLength":2061615,"LastWriteTime":"2026-02-18T22:07:28.8192492+00:00"},"gb/ThXX/TU6NDeV7SyjJFjNAh4TUhaXV4nOba78LvDg=":{"Identity":"C:\\Users\\ADMIN\\source\\repos\\ImagenesService\\ImagenesService\\wwwroot\\imagenes\\usuarios\\1aa3af63-4832-4439-a5e5-e562755a2dfa.png","SourceId":"ImagenesService","SourceType":"Discovered","ContentRoot":"C:\\Users\\ADMIN\\source\\repos\\ImagenesService\\ImagenesService\\wwwroot\\","BasePath":"_content/ImagenesService","RelativePath":"imagenes/usuarios/1aa3af63-4832-4439-a5e5-e562755a2dfa#[.{fingerprint}]?.png","AssetKind":"All","AssetMode":"All","AssetRole":"Primary","AssetMergeBehavior":null,"AssetMergeSource":"","RelatedAsset":null,"AssetTraitName":null,"AssetTraitValue":null,"Fingerprint":"eneo61xgvw","Integrity":"Ktp5idWeJZMhx37FP7/9i9KGD4Qjobk0wjVDLEvXRvU=","CopyToOutputDirectory":"Never","CopyToPublishDirectory":"PreserveNewest","OriginalItemSpec":"wwwroot\\imagenes\\usuarios\\1aa3af63-4832-4439-a5e5-e562755a2dfa.png","FileLength":2327258,"LastWriteTime":"2026-02-18T22:23:16.6286424+00:00"}},"CachedCopyCandidates":{}}